{
    "name": "Theobald, Günzburg",
    "base": "Male | Lochmoor - Shifter",
    "traits": {
        "appearance": "is exceptionally ugly",
        "abilities": "is powerful, brawny, and strong as an ox, but is oblivious and absentminded"
    },
    "personality": {
        "talent": "Great with children",
        "mannerism": "Often brags that they once’s traveled as an adventurer does, until they took a magic missile to the knee ",
        "interaction": "is always honest with the Party"
    },
    "voice": {
        "accent": "None",
        "vocals": "Speaks Normally, at a High pitch.",
        "texture": "Has a Nasal-y voice.",
        "quirk": "doesn't conjugate well ('me make good soup')"
    }
}