{
    "name": "Agrippina, Nesemkhue",
    "base": "Female | Akti - Goblin",
    "traits": {
        "appearance": "wears ragged, dirty clothes",
        "abilities": "is hardy, hale, and healthy, but is dull and boring"
    },
    "personality": {
        "talent": "Great with animals",
        "mannerism": "Never sits down while talking ",
        "interaction": "is quiet around the party"
    },
    "voice": {
        "accent": "None",
        "vocals": "Speaks Slowly, at a Normal pitch.",
        "texture": "Has a Wolfish voice.",
        "quirk": "stuffy nose"
    }
}