{
    "name": "Dae-Jung, Kan",
    "base": "Enby | Usuhan - Aaracokra",
    "traits": {
        "appearance": "is exceptionally beautiful",
        "abilities": "is perceptive, spiritual, and insightful, but is dull and boring"
    },
    "personality": {
        "talent": "None",
        "mannerism": "Never sits down while talking ",
        "interaction": "is easily irritated by the Party"
    },
    "voice": {
        "accent": "Korean",
        "vocals": "Speaks Quickly, at a Normal pitch.",
        "texture": "Has a Strained voice.",
        "quirk": "always pouting"
    }
}