{
    "name": "Crispus, Nefere",
    "base": "Male | Akti - Goblin",
    "traits": {
        "appearance": "is missing teeth",
        "abilities": "is studious, learned, and inquisitive, but is feeble and scrawny"
    },
    "personality": {
        "talent": "None",
        "mannerism": "Intense dislike to a particular race/PC ",
        "interaction": "is argumentative with the Party"
    },
    "voice": {
        "accent": "Mediterranean",
        "vocals": "Speaks Quickly, at a Low pitch.",
        "texture": "Has a Nasal-y voice.",
        "quirk": "Never uses am/is/are/was/were ('I big.' 'She pretty.')"
    }
}